Metadata-Version: 2.1
Name: env2json
Version: 2020.7.1
Summary: .env -> .env.json
Home-page: https://github.com/andrewp-as-is/env2json.py
License: Unlicense
Keywords: env json
Platform: UNKNOWN
Classifier: License :: Public Domain
Classifier: Operating System :: OS Independent
Classifier: Programming Language :: Python :: 3
